dbt/adapters/glue/__init__.py
dbt/adapters/glue/__version__.py
dbt/adapters/glue/column.py
dbt/adapters/glue/connections.py
dbt/adapters/glue/credentials.py
dbt/adapters/glue/impl.py
dbt/adapters/glue/lakeformation.py
dbt/adapters/glue/python_submissions.py
dbt/adapters/glue/relation.py
dbt/adapters/glue/util.py
dbt/adapters/glue/gluedbapi/__init__.py
dbt/adapters/glue/gluedbapi/commons.py
dbt/adapters/glue/gluedbapi/connection.py
dbt/adapters/glue/gluedbapi/cursor.py
dbt/include/glue/__init__.py
dbt/include/glue/dbt_project.yml
dbt/include/glue/sample_profiles.yml
dbt/include/glue/macros/adapters.sql
dbt/include/glue/macros/iceberg_helper.sql
dbt/include/glue/macros/generic_test_sql/accepted_values.sql
dbt/include/glue/macros/generic_test_sql/relationships.sql
dbt/include/glue/macros/materializations/__init__.sql
dbt/include/glue/macros/materializations/seed.sql
dbt/include/glue/macros/materializations/snapshot.sql
dbt/include/glue/macros/materializations/table.sql
dbt/include/glue/macros/materializations/view.sql
dbt/include/glue/macros/materializations/incremental/incremental.sql
dbt/include/glue/macros/materializations/incremental/strategies.sql
dbt/include/glue/macros/materializations/incremental/validate.sql
dbt/include/glue/macros/materializations/python/__init__.sql
dbt/include/glue/macros/materializations/python/python_incremental.sql
dbt/include/glue/macros/materializations/python/python_model.sql
dbt/include/glue/macros/materializations/python/python_utils.sql
dbt/include/glue/macros/python_model/python.sql
dbt/include/glue/macros/utils/make_target_relation.sql
dbt/include/glue/tests/generic/builtin.sql
dbt_glue-1.10.13.dist-info/licenses/LICENSE
dbt_glue-1.10.13.dist-info/licenses/NOTICE
dbt_glue-1.10.13.dist-info/METADATA
dbt_glue-1.10.13.dist-info/WHEEL
dbt_glue-1.10.13.dist-info/top_level.txt
dbt_glue-1.10.13.dist-info/RECORD
