Metadata-Version: 2.4
Name: dbt-glue
Version: 1.10.13
Summary: dbt adapter for AWS Glue
Home-page: https://github.com/aws-samples/dbt-glue
Author: moshirm,segnina,sekiyama
Author-email: moshirm@amazon.fr, segnina@amazon.fr, sekiyama@amazon.com
Classifier: Development Status :: 4 - Beta
Classifier: License :: OSI Approved :: Apache Software License
Classifier: Operating System :: Microsoft :: Windows
Classifier: Operating System :: MacOS :: MacOS X
Classifier: Operating System :: POSIX :: Linux
Classifier: Programming Language :: Python :: 3.9
Classifier: Programming Language :: Python :: 3.10
Classifier: Programming Language :: Python :: 3.11
Requires-Python: >=3.9
License-File: LICENSE
License-File: NOTICE
Requires-Dist: dbt-core~=1.10.13
Requires-Dist: dbt-spark~=1.9.3
Requires-Dist: dbt-common<3.0,>=1.0.4
Requires-Dist: dbt-adapters<2.0,>=1.1.1
Requires-Dist: waiter
Requires-Dist: pyarrow
Requires-Dist: boto3>=1.28.16
Dynamic: author
Dynamic: author-email
Dynamic: classifier
Dynamic: description
Dynamic: description-content-type
Dynamic: home-page
Dynamic: license-file
Dynamic: requires-dist
Dynamic: requires-python
Dynamic: summary
